baca/__init__.py
baca/__main__.py
baca/app.py
baca/components/__init__.py
baca/components/contents.py
baca/components/events.py
baca/components/windows.py
baca/config.py
baca/db.py
baca/ebooks/__init__.py
baca/ebooks/azw.py
baca/ebooks/base.py
baca/ebooks/epub.py
baca/ebooks/mobi.py
baca/exceptions.py
baca/models.py
baca/resources/__init__.py
baca/resources/config.ini
baca/resources/style.css
baca/tools/KindleUnpack/__init__.py
baca/tools/KindleUnpack/compatibility_utils.py
baca/tools/KindleUnpack/kindleunpack.py
baca/tools/KindleUnpack/mobi_cover.py
baca/tools/KindleUnpack/mobi_dict.py
baca/tools/KindleUnpack/mobi_header.py
baca/tools/KindleUnpack/mobi_html.py
baca/tools/KindleUnpack/mobi_index.py
baca/tools/KindleUnpack/mobi_k8proc.py
baca/tools/KindleUnpack/mobi_k8resc.py
baca/tools/KindleUnpack/mobi_nav.py
baca/tools/KindleUnpack/mobi_ncx.py
baca/tools/KindleUnpack/mobi_opf.py
baca/tools/KindleUnpack/mobi_pagemap.py
baca/tools/KindleUnpack/mobi_sectioner.py
baca/tools/KindleUnpack/mobi_split.py
baca/tools/KindleUnpack/mobi_uncompress.py
baca/tools/KindleUnpack/mobi_utils.py
baca/tools/KindleUnpack/mobiml2xhtml.py
baca/tools/KindleUnpack/unipath.py
baca/tools/KindleUnpack/unpack_structure.py
baca/tools/__init__.py
baca/utils/__init__.py
baca/utils/app_resources.py
baca/utils/cli.py
baca/utils/html_parser.py
baca/utils/keys_parser.py
baca/utils/queries.py
baca/utils/systems.py
baca/utils/tempdir.py
baca/utils/urls.py
baca/utils/user_appdirs.py
baca-0.1.17.dist-info/entry_points.txt
baca-0.1.17.dist-info/LICENSE
baca-0.1.17.dist-info/WHEEL
baca-0.1.17.dist-info/METADATA
baca-0.1.17.dist-info/RECORD
